{"cameraMode":{"drawMode":0,"name":"Shaded","section":"Shading Mode"},"sceneLighting":true,"audioPlay":false,"sceneViewState":{"showFog":true,"showMaterialUpdate":false,"showSkybox":true,"showFlares":true,"showImageEffects":true,"showParticleSystems":true},"in2DMode":false,"pivot":{"x":-22.4291934967041,"y":-42.227535247802737,"z":37.386112213134769},"rotation":{"x":0.3485206663608551,"y":-0.2141566127538681,"z":0.08276597410440445,"w":0.9088738560676575},"size":42.61336135864258,"orthographic":false}